aliyunsdkpaistudio/__init__.py
aliyunsdkpaistudio/endpoint.py
aliyunsdkpaistudio/request/__init__.py
aliyunsdkpaistudio/request/v20220112/CreateAlgorithmRequest.py
aliyunsdkpaistudio/request/v20220112/CreateAlgorithmVersionRequest.py
aliyunsdkpaistudio/request/v20220112/CreateResourceGroupRequest.py
aliyunsdkpaistudio/request/v20220112/CreateTrainingJobRequest.py
aliyunsdkpaistudio/request/v20220112/DeleteMachineGroupRequest.py
aliyunsdkpaistudio/request/v20220112/DeleteResourceGroupMachineGroupRequest.py
aliyunsdkpaistudio/request/v20220112/DeleteResourceGroupRequest.py
aliyunsdkpaistudio/request/v20220112/GetAlgorithmRequest.py
aliyunsdkpaistudio/request/v20220112/GetAlgorithmVersionRequest.py
aliyunsdkpaistudio/request/v20220112/GetMachineGroupRequest.py
aliyunsdkpaistudio/request/v20220112/GetNodeMetricsRequest.py
aliyunsdkpaistudio/request/v20220112/GetResourceGroupMachineGroupRequest.py
aliyunsdkpaistudio/request/v20220112/GetResourceGroupRequest.py
aliyunsdkpaistudio/request/v20220112/GetResourceGroupRequestRequest.py
aliyunsdkpaistudio/request/v20220112/GetResourceGroupTotalRequest.py
aliyunsdkpaistudio/request/v20220112/GetTrainingJobRequest.py
aliyunsdkpaistudio/request/v20220112/ListAlgorithmVersionsRequest.py
aliyunsdkpaistudio/request/v20220112/ListAlgorithmsRequest.py
aliyunsdkpaistudio/request/v20220112/ListResourceGroupMachineGroupsRequest.py
aliyunsdkpaistudio/request/v20220112/ListResourceGroupsRequest.py
aliyunsdkpaistudio/request/v20220112/ListTrainingJobLogsRequest.py
aliyunsdkpaistudio/request/v20220112/ListTrainingJobMetricsRequest.py
aliyunsdkpaistudio/request/v20220112/UpdateAlgorithmRequest.py
aliyunsdkpaistudio/request/v20220112/UpdateAlgorithmVersionRequest.py
aliyunsdkpaistudio/request/v20220112/UpdateResourceGroupRequest.py
aliyunsdkpaistudio/request/v20220112/__init__.py
aliyun_python_sdk_paistudio-1.0.0.dist-info/LICENSE
aliyun_python_sdk_paistudio-1.0.0.dist-info/METADATA
aliyun_python_sdk_paistudio-1.0.0.dist-info/WHEEL
aliyun_python_sdk_paistudio-1.0.0.dist-info/top_level.txt
aliyun_python_sdk_paistudio-1.0.0.dist-info/RECORD
